topopy-1.0.4.dist-info/LICENSE
topopy-1.0.4.dist-info/top_level.txt
topopy-1.0.4.dist-info/WHEEL
topopy-1.0.4.dist-info/RECORD
topopy-1.0.4.dist-info/METADATA
topopy/MorseComplex.py
topopy/_topology.pypy37-pp73-x86_64-linux-gnu.so
topopy/MergeTree.py
topopy/TopologicalObject.py
topopy/MorseSmaleComplex.py
topopy/ContourTree.py
topopy/topology.py
topopy/__init__.py
topopy/tests/test_mc.py
topopy/tests/mc_gold.json
topopy/tests/test_mt.py
topopy/tests/test_to.py
topopy/tests/msc_gold.json
topopy/tests/test_functions.py
topopy/tests/test_ct.py
topopy/tests/test_msc.py
topopy/tests/__init__.py
