Metadata-Version: 2.1
Name: topopy
Version: 1.0.4
Summary: A library for computing topological data structures
Author-email: Dan Maljovec <maljovec002@gmail.com>
Project-URL: Documentation, https://topopy.readthedocs.io/en/latest/
Project-URL: Source, https://github.com/maljovec/topopy
Keywords: topological data analysis,computational topology,Morse theory,merge tree,contour tree,extremum graph,Morse-Smale complex,Morse complex
Classifier: Development Status :: 3 - Alpha
Classifier: Intended Audience :: Science/Research
Classifier: License :: OSI Approved :: BSD License
Classifier: Programming Language :: C++
Classifier: Programming Language :: Python :: 3
Classifier: Topic :: Scientific/Engineering :: Mathematics
Requires-Python: >=2.7, <4
License-File: LICENSE
